.coveragerc
.travis.yml
CHANGES.rst
CONTRIBUTORS.rst
MANIFEST.in
README.rst
bootstrap-buildout.py
buildout.cfg
setup.py
travis.cfg
docs/LICENSE.GPL
docs/LICENSE.rst
docs/index.rst
src/collective/__init__.py
src/collective.querynextprev.egg-info/PKG-INFO
src/collective.querynextprev.egg-info/SOURCES.txt
src/collective.querynextprev.egg-info/dependency_links.txt
src/collective.querynextprev.egg-info/entry_points.txt
src/collective.querynextprev.egg-info/namespace_packages.txt
src/collective.querynextprev.egg-info/not-zip-safe
src/collective.querynextprev.egg-info/requires.txt
src/collective.querynextprev.egg-info/top_level.txt
src/collective/querynextprev/__init__.py
src/collective/querynextprev/configure.zcml
src/collective/querynextprev/interfaces.py
src/collective/querynextprev/setuphandlers.py
src/collective/querynextprev/subscribers.py
src/collective/querynextprev/subscribers.zcml
src/collective/querynextprev/testing.py
src/collective/querynextprev/upgrades.py
src/collective/querynextprev/upgrades.zcml
src/collective/querynextprev/utils.py
src/collective/querynextprev/browser/__init__.py
src/collective/querynextprev/browser/configure.zcml
src/collective/querynextprev/browser/viewlets.py
src/collective/querynextprev/browser/views.py
src/collective/querynextprev/browser/static/.gitkeep
src/collective/querynextprev/browser/templates/nextprev.pt
src/collective/querynextprev/locales/collective.querynextprev.pot
src/collective/querynextprev/locales/update.sh
src/collective/querynextprev/locales/fr/LC_MESSAGES/collective.querynextprev.po
src/collective/querynextprev/profiles/default/browserlayer.xml
src/collective/querynextprev/profiles/default/collectivequerynextprev_default.txt
src/collective/querynextprev/profiles/default/metadata.xml
src/collective/querynextprev/profiles/default/registry.xml
src/collective/querynextprev/profiles/default/viewlets.xml
src/collective/querynextprev/tests/__init__.py
src/collective/querynextprev/tests/test_setup.py
src/collective/querynextprev/tests/test_subscribers.py
src/collective/querynextprev/tests/test_utils.py
src/collective/querynextprev/tests/test_viewlets.py
src/collective/querynextprev/tests/test_views.py