Metadata-Version: 1.1
Name: collective.querynextprev
Version: 0.4
Summary: Navigate through your query results using a next and a previous buttons
Home-page: http://pypi.python.org/pypi/collective.querynextprev
Author: Cédric Messiant
Author-email: cedricmessiant@ecreall.com
License: GPL version 2
Keywords: Python Plone
Platform: UNKNOWN
Classifier: Environment :: Web Environment
Classifier: Framework :: Plone
Classifier: Framework :: Plone :: 4.3
Classifier: Programming Language :: Python
Classifier: Programming Language :: Python :: 2.7
Classifier: Operating System :: OS Independent
Classifier: License :: OSI Approved :: GNU General Public License v2 (GPLv2)
